{"chunk_definitions":[{"chunk_id":"c30dlkm9vh1t6","chunk_label":"unnamed-chunk-1","document_id":"D67AE4A7","expansion_state":0,"options":{"engine":"r","label":"unnamed-chunk-6"},"row":18,"row_count":1,"visible":true},{"chunk_id":"ce56yl28b4rkj","chunk_label":"unnamed-chunk-2","document_id":"D67AE4A7","expansion_state":0,"options":{"engine":"r","label":"unnamed-chunk-7"},"row":31,"row_count":1,"visible":true},{"chunk_id":"cn9zk94gcvkuu","chunk_label":"unnamed-chunk-3","document_id":"D67AE4A7","expansion_state":0,"options":{"engine":"r","label":"unnamed-chunk-8"},"row":116,"row_count":1,"visible":true},{"chunk_id":"cylrppuno3fcb","chunk_label":"unnamed-chunk-4","document_id":"D67AE4A7","expansion_state":0,"options":{"engine":"r","label":"unnamed-chunk-9"},"row":135,"row_count":1,"visible":true},{"chunk_id":"cal4fs7xgpds9","chunk_label":"unnamed-chunk-5","document_id":"D67AE4A7","expansion_state":0,"options":{"engine":"r","label":"unnamed-chunk-11"},"row":160,"row_count":1,"visible":true}],"chunk_rendered_width":700,"doc_write_time":1508444354}